depends_tools/__init__.py
depends_tools/call_factory.py
depends_tools/context.py
depends_tools/d_type.py
depends_tools/depends.py
depends_tools/injector.py
depends_tools/resolver.py
depends_tools/util.py
depends_tools-1.1.0.dist-info/licenses/LICENSE
depends_tools-1.1.0.dist-info/METADATA
depends_tools-1.1.0.dist-info/WHEEL
depends_tools-1.1.0.dist-info/top_level.txt
depends_tools-1.1.0.dist-info/RECORD
