Metadata-Version: 2.4
Name: depends-tools
Version: 1.1.0
Summary: A Python dependency injection framework, it's like fastapi.Depends
Author: surp1us
Project-URL: Homepage, https://github.com/JokerCrying/py-depends-tools
Project-URL: Repository, https://github.com/JokerCrying/py-depends-tools
Project-URL: Bug Tracker, https://github.com/JokerCrying/py-depends-tools/issues
Keywords: dependency,injection,di,ioc
Classifier: Development Status :: 3 - Alpha
Classifier: Intended Audience :: Developers
Classifier: License :: OSI Approved :: MIT License
Classifier: Programming Language :: Python :: 3
Classifier: Programming Language :: Python :: 3.7
Classifier: Programming Language :: Python :: 3.8
Classifier: Programming Language :: Python :: 3.9
Classifier: Programming Language :: Python :: 3.10
Classifier: Programming Language :: Python :: 3.11
Requires-Python: >=3.7
License-File: LICENSE
Provides-Extra: dev
Requires-Dist: pytest>=6.0; extra == "dev"
Requires-Dist: pytest-asyncio; extra == "dev"
Requires-Dist: black; extra == "dev"
Requires-Dist: flake8; extra == "dev"
Requires-Dist: mypy; extra == "dev"
Provides-Extra: docs
Requires-Dist: sphinx; extra == "docs"
Requires-Dist: sphinx-rtd-theme; extra == "docs"
Dynamic: license-file
